README.rst
afinder.py
setup.py
./afinder.py
./test_afinder.py
afinder.egg-info/PKG-INFO
afinder.egg-info/SOURCES.txt
afinder.egg-info/dependency_links.txt
afinder.egg-info/namespace_packages.txt
afinder.egg-info/not-zip-safe
afinder.egg-info/pbr.json
afinder.egg-info/requires.txt
afinder.egg-info/top_level.txt