Metadata-Version: 1.1
Name: afinder
Version: 0.0.3
Summary: find attribute in deep object
Home-page: https://github.com/kaporzhu/afinder
Author: Kapor Zhu
Author-email: kapor.zhu@gmail.com
License: Apache 2.0
Platform: UNKNOWN
Classifier: Development Status :: 3 - Alpha
Classifier: Intended Audience :: Developers
Classifier: Natural Language :: English
Classifier: License :: OSI Approved :: Apache Software License
Classifier: Programming Language :: Python
Classifier: Programming Language :: Python :: 2.7
Classifier: Programming Language :: Python :: 3
Classifier: Programming Language :: Python :: 3.5
